exceptionless/ExceptionlessStatics.py
exceptionless/ExceptionlessUtils.py
exceptionless/System.py
exceptionless/__init__.py
exceptionless/exception/ExceptionlessError.py
exceptionless-0.1.0.dist-info/licenses/LICENSE
exceptionless-0.1.0.dist-info/METADATA
exceptionless-0.1.0.dist-info/WHEEL
exceptionless-0.1.0.dist-info/top_level.txt
exceptionless-0.1.0.dist-info/RECORD
