Metadata-Version: 2.4
Name: exceptionless
Version: 0.1.0
Summary: A Python client for Exceptionless
Author-email: adrievx <adrievx@hotmail.com>
License: MIT License
Project-URL: Homepage, https://github.com/adrievx/exceptionless-python
Project-URL: Issues, https://github.com/adrievx/exceptionless-python/issues
Requires-Python: >=3.8
License-File: LICENSE
Requires-Dist: requests>=2.28
Dynamic: license-file
